amis/__init__.py
amis/core/__init__.py
amis/core/config.py
amis/core/exceptions.py
amis/core/manager.py
amis/core/module.py
amis/core/input/__init__.py
amis/core/input/console.py
amis/core/output/__init__.py
amis/core/output/console.py
amis/core/person/__init__.py
amis/core/person/input.py
amis/core/person/output.py
amis/modules/__init__.py
amis/modules/media_control.py
amis/modules/test_module.py
amis/tests/__init__.py
amis/tests/config_test.py
amis/tests/manager_test.py
amis/tests/module_test.py
amis/tests/person_test.py
mia_amis-0.1.0.1.dist-info/METADATA
mia_amis-0.1.0.1.dist-info/WHEEL
mia_amis-0.1.0.1.dist-info/top_level.txt
mia_amis-0.1.0.1.dist-info/RECORD
