Metadata-Version: 2.4
Name: mia-amis
Version: 0.1.0.1
Summary: Assistant Module Interface System
Author: RayzorST
Project-URL: Homepage, https://github.com/RayzorST/Assistant-Module-Interface-System
Classifier: Development Status :: 3 - Alpha
Classifier: Intended Audience :: Developers
Classifier: Programming Language :: Python :: 3.8
Classifier: Programming Language :: Python :: 3.9
Classifier: Programming Language :: Python :: 3.10
Classifier: Programming Language :: Python :: 3.11
Classifier: Operating System :: OS Independent
Classifier: Topic :: Software Development :: Libraries :: Application Frameworks
Requires-Python: >=3.8
Requires-Dist: watchdog>=2.0.0
Requires-Dist: keyboard>=0.13.5
Provides-Extra: dev
Requires-Dist: pytest>=6.0; extra == "dev"
Requires-Dist: black>=21.0; extra == "dev"
Requires-Dist: mypy>=0.900; extra == "dev"
Requires-Dist: flake8>=3.9; extra == "dev"
